Workbook

Sheet Product Backlog
A1: PRODUCT BACKLOG · Simulador de riego presurizado
A2: Sosa Colca, Angello Rodolfo · Tongo Alejandro, Milagros Salet · Ingeniería de Software, UPC. 30 historias en 4 sprints de dos semanas, cada una con sus criterios de aceptación. Una historia se da por terminada solo cuando se cumplen todos.
A4: ID | B4: ÉPICA | C4: COMO... | D4: QUIERO... | E4: PARA... | F4: CRITERIOS DE ACEPTACIÓN | G4: PRIORIDAD | H4: SPRINT | I4: ESTADO
A5: HU-01 | B5: E1 · Motor de cálculo verificado | C5: Equipo de desarrollo | D5: un motor de cálculo separado de la pantalla, que resuelva la red abierta recorriéndola nodo por nodo | E5: poder verificarlo por sí solo, reutilizarlo en la pantalla y en el optimizador, y que el resultado aparezca en menos de doscientos milisegundos | F5: 1. El motor se ejecuta sin abrir la interfaz, desde una prueba automática. 2. Una red de cincuenta nodos se resuelve completa en menos de doscientos milisegundos. 3. El recorrido acumula caudales de las salidas hacia el origen y propaga presiones del origen hacia las salidas, pasando una sola vez por cada nodo. | G5: Alta | H5: Sprint 1 | I5: Pendiente
A6: HU-02 | B6: E1 · Motor de cálculo verificado | C6: Equipo de desarrollo | D6: calcular la pérdida de carga con Hazen-Williams sobre la longitud inclinada del tramo y sumar las pérdidas locales de los accesorios | E6: reproducir el método de la hoja profesional de referencia, con entradas, codos, ampliaciones y reducciones incluidas | F6: 1. La longitud de cálculo de cada tramo es la inclinada, no la proyección horizontal. 2. Un problema resuelto de bibliografía se reproduce con la misma pérdida de carga hasta el tercer decimal. 3. Las pérdidas locales se suman con el coeficiente de cada accesorio y se pueden desactivar para comparar el efecto. | G6: Alta | H6: Sprint 1 | I6: Pendiente
A7: HU-03 | B7: E1 · Motor de cálculo verificado | C7: Equipo de desarrollo | D7: que el caudal de cada emisor salga de su curva característica, y resolver por aproximaciones sucesivas el acoplamiento entre presión y caudal | E7: que lo que entrega cada salida corresponda a la presión real que tiene, y no todas entreguen lo mismo aunque sean iguales | F7: 1. El caudal de cada salida se obtiene de su curva, con el exponente configurable para emisor simple y autocompensante. 2. Las aproximaciones se detienen cuando el caudal varía menos de una décima de por ciento entre dos vueltas. 3. Dos salidas del mismo modelo con distinta presión entregan caudales distintos. | G7: Alta | H7: Sprint 1 | I7: Pendiente
A8: HU-04 | B8: E1 · Motor de cálculo verificado | C8: Equipo de desarrollo | D8: aplicar las cámaras rompe-presión y las válvulas reguladoras como condiciones del recorrido | E8: que corten la carga exactamente donde el estudiante las coloque | F8: 1. Aguas abajo de una cámara rompe-presión la carga vuelve a la altura de la cámara, sin arrastrar la presión anterior. 2. Una válvula reguladora fija la presión de salida al valor configurado mientras la de entrada sea mayor. 3. Quitar el elemento devuelve la red exactamente al estado que tenía antes de colocarlo. | G8: Alta | H8: Sprint 1 | I8: Pendiente
A9: HU-05 | B9: E1 · Motor de cálculo verificado | C9: Equipo de desarrollo | D9: una tabla de verificación del motor contra la hoja profesional, un simulador estándar y problemas resueltos de bibliografía, y pruebas automáticas sobre redes generadas al azar que corran en cada cambio | E9: demostrar con error documentado que el cálculo es correcto antes de que ningún estudiante lo use | F9: 1. Existe una tabla que compara, tramo por tramo, el resultado del motor con las tres fuentes. 2. El error frente a la hoja de referencia queda documentado y por debajo de una centésima de por ciento. 3. Las pruebas corren en cada cambio del código y fallan si se rompe una invariante física, por ejemplo si la presión sube en el sentido del flujo sin una bomba. | G9: Alta | H9: Sprint 1 | I9: Pendiente
A10: HU-06 | B10: E9 · Instrumentación y validación | C10: Docente | D10: un banco de ítems clasificado por nivel cognitivo y asociado a cada una de las siete creencias equivocadas del inventario | E10: que el instrumento mida comprensión y no destreza de cálculo | F10: 1. Cada ítem declara a qué creencia equivocada corresponde y en qué nivel de la taxonomía se ubica. 2. Hay al menos dos ítems por cada una de las siete creencias. 3. Al menos un tercio del banco está en los niveles de Analizar y Evaluar, y ningún ítem se resuelve aplicando una fórmula con los datos dados. | G10: Alta | H10: Sprint 1 | I10: Pendiente
A11: HU-07 | B11: E9 · Instrumentación y validación | C11: Docente | D11: someter el instrumento a juicio de un docente de hidráulica y a una prueba piloto | E11: poder afirmar que lo que mide es lo que dice medir | F11: 1. Al menos dos docentes de hidráulica revisan el banco y su conformidad queda registrada ítem por ítem. 2. Se aplica a un grupo piloto ajeno al experimento y se calcula la consistencia interna. 3. Los ítems que el piloto muestre ambiguos, o que nadie responda bien, se corrigen o se retiran antes del pretest. | G11: Alta | H11: Sprint 1 | I11: Pendiente
A12: HU-08 | B12: E10 · Cuentas y sesión | C12: Estudiante y docente | D12: entrar con mi cuenta, con permisos distintos según mi rol, y que mis diseños queden guardados con su número de versión | E12: retomar donde dejé, ver mi propia trayectoria de mejora y, si soy docente, seguir el avance del grupo | F12: 1. El estudiante ve solo sus diseños y el docente ve los de su grupo. 2. Cada guardado crea una versión nueva y las anteriores siguen abiertas para consulta. 3. Cerrar el navegador y volver a entrar devuelve el último diseño en el punto donde quedó. | G12: Media | H12: Sprint 2 | I12: Pendiente
A13: HU-09 | B13: E2 · Diseño en 2D | C13: Estudiante | D13: ver a la vez la planta a escala real, el perfil con el terreno, la tubería y la línea de presión disponible, y la tabla por tramo con las columnas y unidades del método de referencia, con el tramo que toco resaltado en las tres y el estado de cada nodo por color | E13: leer el mismo hecho de tres maneras y reconocer de un vistazo dónde falta presión y dónde sobra | F13: 1. Las tres vistas se ven al mismo tiempo, sin cambiar de pantalla ni de pestaña. 2. Seleccionar un tramo en cualquiera de las tres lo resalta en las otras dos. 3. El perfil dibuja terreno, tubería y línea de presión disponible, y la franja entre las dos últimas se lee como la presión de ese punto. 4. Cada nodo toma color según si le falta presión, está en rango o le sobra. | G13: Alta | H13: Sprint 2 | I13: Pendiente
A14: HU-10 | B14: E2 · Diseño en 2D | C14: Estudiante | D14: editar el diámetro, la clase, los accesorios y la cota desde la propia tabla y ver el efecto al instante | E14: probar alternativas sin cambiar de pantalla y entender cuánta presión regala o cobra la topografía | F14: 1. Cambiar cualquiera de esos valores actualiza las tres vistas sin recargar la página. 2. El resultado aparece en menos de un segundo desde el cambio. 3. Se puede deshacer el último cambio y volver al valor anterior. | G14: Alta | H14: Sprint 2 | I14: Pendiente
A15: HU-11 | B15: E6 · Terreno y vista 3D | C15: Docente | D15: escenarios construidos sobre perfiles reales de zonas de riego peruanas, que yo pueda publicar para mi grupo | E15: que la práctica no ocurra sobre un terreno inventado, y dirigirla sin depender del equipo de desarrollo | F15: 1. Cada escenario trae un perfil real de una zona de riego peruana, con su procedencia anotada. 2. El docente publica un escenario a su grupo y lo retira, sin intervención del equipo de desarrollo. 3. Hay al menos tres escenarios con relieves distintos: ladera, terraza y terreno quebrado. | G15: Alta | H15: Sprint 2 | I15: Pendiente
... A34: HU-30 | B34: E8 · Reporte y entrega | C34: Estudiante y docente | D34: exportar el diseño final en PDF con el plano, la tabla completa, los parámetros, los indicadores y el origen de cada decisión, y exportar los resultados del grupo en un formato analizable | E34: entregarlo como trabajo, dejar claro qué decidí yo y qué adopté del optimizador, y hacer el análisis estadístico fuera de la aplicación | F34: 1. El PDF incluye el plano, la tabla completa por tramo, los parámetros de entrada y los indicadores finales. 2. Cada decisión aparece marcada como propia del estudiante o adoptada del optimizador. 3. El docente exporta los resultados del grupo en un formato que abre una herramienta estadística, sin datos que identifiquen a nadie. | G34: Alta | H34: Sprint 4 | I34: Pendiente

Sheet Resumen
A1: RESUMEN DEL BACKLOG
A3: Historias por épica
A4: ÉPICA | B4: TOTAL | C4: SPRINT 1 | D4: SPRINT 2 | E4: SPRINT 3 | F4: SPRINT 4
A5: E1 · Motor de cálculo verificado | B5: =COUNTIF('Product Backlog'!$B$5:$B$34,$A5) -> 5 | C5: =COUNTIFS('Product Backlog'!$B$5:$B$34,$A5,'Product Backlog'!$H$5:$H$34,"Sprint 1") -> 5 | D5: =COUNTIFS('Product Backlog'!$B$5:$B$34,$A5,'Product Backlog'!$H$5:$H$34,"Sprint 2") -> 0 | E5: =COUNTIFS('Product Backlog'!$B$5:$B$34,$A5,'Product Backlog'!$H$5:$H$34,"Sprint 3") -> 0 | F5: =COUNTIFS('Product Backlog'!$B$5:$B$34,$A5,'Product Backlog'!$H$5:$H$34,"Sprint 4") -> 0
A6: E2 · Diseño en 2D | B6: =COUNTIF('Product Backlog'!$B$5:$B$34,$A6) -> 2 | C6: =COUNTIFS('Product Backlog'!$B$5:$B$34,$A6,'Product Backlog'!$H$5:$H$34,"Sprint 1") -> 0 | D6: =COUNTIFS('Product Backlog'!$B$5:$B$34,$A6,'Product Backlog'!$H$5:$H$34,"Sprint 2") -> 2 | E6: =COUNTIFS('Product Backlog'!$B$5:$B$34,$A6,'Product Backlog'!$H$5:$H$34,"Sprint 3") -> 0 | F6: =COUNTIFS('Product Backlog'!$B$5:$B$34,$A6,'Product Backlog'!$H$5:$H$34,"Sprint 4") -> 0
A7: E3 · Base agronómica | B7: =COUNTIF('Product Backlog'!$B$5:$B$34,$A7) -> 3 | C7: =COUNTIFS('Product Backlog'!$B$5:$B$34,$A7,'Product Backlog'!$H$5:$H$34,"Sprint 1") -> 0 | D7: =COUNTIFS('Product Backlog'!$B$5:$B$34,$A7,'Product Backlog'!$H$5:$H$34,"Sprint 2") -> 0 | E7: =COUNTIFS('Product Backlog'!$B$5:$B$34,$A7,'Product Backlog'!$H$5:$H$34,"Sprint 3") -> 3 | F7: =COUNTIFS('Product Backlog'!$B$5:$B$34,$A7,'Product Backlog'!$H$5:$H$34,"Sprint 4") -> 0
A8: E4 · Proceso de aprendizaje | B8: =COUNTIF('Product Backlog'!$B$5:$B$34,$A8) -> 4 | C8: =COUNTIFS('Product Backlog'!$B$5:$B$34,$A8,'Product Backlog'!$H$5:$H$34,"Sprint 1") -> 0 | D8: =COUNTIFS('Product Backlog'!$B$5:$B$34,$A8,'Product Backlog'!$H$5:$H$34,"Sprint 2") -> 0 | E8: =COUNTIFS('Product Backlog'!$B$5:$B$34,$A8,'Product Backlog'!$H$5:$H$34,"Sprint 3") -> 4 | F8: =COUNTIFS('Product Backlog'!$B$5:$B$34,$A8,'Product Backlog'!$H$5:$H$34,"Sprint 4") -> 0
A9: E5 · Presión, uniformidad y costos | B9: =COUNTIF('Product Backlog'!$B$5:$B$34,$A9) -> 2 | C9: =COUNTIFS('Product Backlog'!$B$5:$B$34,$A9,'Product Backlog'!$H$5:$H$34,"Sprint 1") -> 0 | D9: =COUNTIFS('Product Backlog'!$B$5:$B$34,$A9,'Product Backlog'!$H$5:$H$34,"Sprint 2") -> 2 | E9: =COUNTIFS('Product Backlog'!$B$5:$B$34,$A9,'Product Backlog'!$H$5:$H$34,"Sprint 3") -> 0 | F9: =COUNTIFS('Product Backlog'!$B$5:$B$34,$A9,'Product Backlog'!$H$5:$H$34,"Sprint 4") -> 0
A10: E6 · Terreno y vista 3D | B10: =COUNTIF('Product Backlog'!$B$5:$B$34,$A10) -> 4 | C10: =COUNTIFS('Product Backlog'!$B$5:$B$34,$A10,'Product Backlog'!$H$5:$H$34,"Sprint 1") -> 0 | D10: =COUNTIFS('Product Backlog'!$B$5:$B$34,$A10,'Product Backlog'!$H$5:$H$34,"Sprint 2") -> 1 | E10: =COUNTIFS('Product Backlog'!$B$5:$B$34,$A10,'Product Backlog'!$H$5:$H$34,"Sprint 3") -> 0 | F10: =COUNTIFS('Product Backlog'!$B$5:$B$34,$A10,'Product Backlog'!$H$5:$H$34,"Sprint 4") -> 3
A11: E7 · Optimización con IA | B11: =COUNTIF('Product Backlog'!$B$5:$B$34,$A11) -> 4 | C11: =COUNTIFS('Product Backlog'!$B$5:$B$34,$A11,'Product Backlog'!$H$5:$H$34,"Sprint 1") -> 0 | D11: =COUNTIFS('Product Backlog'!$B$5:$B$34,$A11,'Product Backlog'!$H$5:$H$34,"Sprint 2") -> 0 | E11: =COUNTIFS('Product Backlog'!$B$5:$B$34,$A11,'Product Backlog'!$H$5:$H$34,"Sprint 3") -> 0 | F11: =COUNTIFS('Product Backlog'!$B$5:$B$34,$A11,'Product Backlog'!$H$5:$H$34,"Sprint 4") -> 4
A12: E8 · Reporte y entrega | B12: =COUNTIF('Product Backlog'!$B$5:$B$34,$A12) -> 1 | C12: =COUNTIFS('Product Backlog'!$B$5:$B$34,$A12,'Product Backlog'!$H$5:$H$34,"Sprint 1") -> 0 | D12: =COUNTIFS('Product Backlog'!$B$5:$B$34,$A12,'Product Backlog'!$H$5:$H$34,"Sprint 2") -> 0 | E12: =COUNTIFS('Product Backlog'!$B$5:$B$34,$A12,'Product Backlog'!$H$5:$H$34,"Sprint 3") -> 0 | F12: =COUNTIFS('Product Backlog'!$B$5:$B$34,$A12,'Product Backlog'!$H$5:$H$34,"Sprint 4") -> 1
A13: E9 · Instrumentación y validación | B13: =COUNTIF('Product Backlog'!$B$5:$B$34,$A13) -> 4 | C13: =COUNTIFS('Product Backlog'!$B$5:$B$34,$A13,'Product Backlog'!$H$5:$H$34,"Sprint 1") -> 2 | D13: =COUNTIFS('Product Backlog'!$B$5:$B$34,$A13,'Product Backlog'!$H$5:$H$34,"Sprint 2") -> 1 | E13: =COUNTIFS('Product Backlog'!$B$5:$B$34,$A13,'Product Backlog'!$H$5:$H$34,"Sprint 3") -> 1 | F13: =COUNTIFS('Product Backlog'!$B$5:$B$34,$A13,'Product Backlog'!$H$5:$H$34,"Sprint 4") -> 0
A14: E10 · Cuentas y sesión | B14: =COUNTIF('Product Backlog'!$B$5:$B$34,$A14) -> 1 | C14: =COUNTIFS('Product Backlog'!$B$5:$B$34,$A14,'Product Backlog'!$H$5:$H$34,"Sprint 1") -> 0 | D14: =COUNTIFS('Product Backlog'!$B$5:$B$34,$A14,'Product Backlog'!$H$5:$H$34,"Sprint 2") -> 1 | E14: =COUNTIFS('Product Backlog'!$B$5:$B$34,$A14,'Product Backlog'!$H$5:$H$34,"Sprint 3") -> 0 | F14: =COUNTIFS('Product Backlog'!$B$5:$B$34,$A14,'Product Backlog'!$H$5:$H$34,"Sprint 4") -> 0
A15: TOTAL | B15: =SUM(B5:B14) -> 30 | C15: =SUM(C5:C14) -> 7 | D15: =SUM(D5:D14) -> 7 | E15: =SUM(E5:E14) -> 8 | F15: =SUM(F5:F14) -> 8
A18: Historias por sprint
A19: SPRINT | B19: TOTAL | C19: PRIORIDAD ALTA | D19: PRIORIDAD MEDIA
A20: Sprint 1 | B20: =COUNTIF('Product Backlog'!$H$5:$H$34,$A20) -> 7 | C20: =COUNTIFS('Product Backlog'!$H$5:$H$34,$A20,'Product Backlog'!$G$5:$G$34,"Alta") -> 7 | D20: =COUNTIFS('Product Backlog'!$H$5:$H$34,$A20,'Product Backlog'!$G$5:$G$34,"Media") -> 0
A21: Sprint 2 | B21: =COUNTIF('Product Backlog'!$H$5:$H$34,$A21) -> 7 | C21: =COUNTIFS('Product Backlog'!$H$5:$H$34,$A21,'Product Backlog'!$G$5:$G$34,"Alta") -> 6 | D21: =COUNTIFS('Product Backlog'!$H$5:$H$34,$A21,'Product Backlog'!$G$5:$G$34,"Media") -> 1
A22: Sprint 3 | B22: =COUNTIF('Product Backlog'!$H$5:$H$34,$A22) -> 8 | C22: =COUNTIFS('Product Backlog'!$H$5:$H$34,$A22,'Product Backlog'!$G$5:$G$34,"Alta") -> 7 | D22: =COUNTIFS('Product Backlog'!$H$5:$H$34,$A22,'Product Backlog'!$G$5:$G$34,"Media") -> 1
A23: Sprint 4 | B23: =COUNTIF('Product Backlog'!$H$5:$H$34,$A23) -> 8 | C23: =COUNTIFS('Product Backlog'!$H$5:$H$34,$A23,'Product Backlog'!$G$5:$G$34,"Alta") -> 6 | D23: =COUNTIFS('Product Backlog'!$H$5:$H$34,$A23,'Product Backlog'!$G$5:$G$34,"Media") -> 2
A24: TOTAL | B24: =SUM(B20:B23) -> 30 | C24: =SUM(C20:C23) -> 26 | D24: =SUM(D20:D23) -> 4
A27: Historias por rol
A28: ROL | B28: TOTAL
A29: Estudiante | B29: =COUNTIF('Product Backlog'!$C$5:$C$34,$A29) -> 17
A30: Docente | B30: =COUNTIF('Product Backlog'!$C$5:$C$34,$A30) -> 4
A31: Equipo de desarrollo | B31: =COUNTIF('Product Backlog'!$C$5:$C$34,$A31) -> 7
A32: Estudiante y docente | B32: =COUNTIF('Product Backlog'!$C$5:$C$34,$A32) -> 2
A33: TOTAL | B33: =SUM(B29:B32) -> 30
A36: Nota de alcance
A37: El backlog anterior tenía 82 historias y dejaba 33 fuera de los sprints, entre ellas todo el 3D y toda la optimización con IA. Al compactar a 30 no se recortó alcance: se agruparon historias que eran partes de una misma entrega, y las tres piezas que sostienen el planteamiento — 2D, 3D e IA — quedan dentro de los cuatro sprints. Los roles son los tres del proyecto: estudiante, docente y equipo de desarrollo.
